README.md
setup.py
LibBraga/Github_api.py
LibBraga/__init__.py
LibBraga.egg-info/PKG-INFO
LibBraga.egg-info/SOURCES.txt
LibBraga.egg-info/dependency_links.txt
LibBraga.egg-info/not-zip-safe
LibBraga.egg-info/requires.txt
LibBraga.egg-info/top_level.txt