Metadata-Version: 2.1
Name: LibBraga
Version: 0.1
Summary: Repositório para exemplificar a criação de projetos no Python
Home-page: https://github.com/htjoao/LibBraga
Author: João Victor
Author-email: jvictor.braga@yahoo.com
License: GNU AFFERO GENERAL PUBLIC LICENSE
Platform: UNKNOWN
Classifier: Development Status :: 2 - Pre-Alpha
Classifier: Environment :: Console
Classifier: Intended Audience :: Developers
Classifier: License :: OSI Approved :: GNU Affero General Public License v3 or later (AGPLv3+)
Classifier: Operating System :: OS Independent
Classifier: Programming Language :: Python
Classifier: Programming Language :: Python :: 3.8
Classifier: Framework :: Pytest
